{
  "checked_at_utc": "2026-07-08 17:13:54",
  "portals": [
    {
      "name": "CPPP - Central Government (all ministries)",
      "state": "Central",
      "tenders_seen": 23,
      "status": "ok",
      "sample_titles": [
        "1. Provision of Plinth Protection for Various Existing Buildings within the Kodaikanal Sol",
        "2.  Systematic maintenance contract of Railway siding at FSD Nagpur during the year 2026-2",
        "3. Remodeling of existing rooms on the ground floor Room Nos. 1 and 3 for the proposed NLS"
      ]
    },
    {
      "name": "Uttar Pradesh",
      "state": "Uttar Pradesh",
      "tenders_seen": 23,
      "status": "ok",
      "sample_titles": [
        "1. COMPETITIVE e-bidding FOR SUPPLY OF COMPUTER STATIONERY FOR VARIOUS COOP SUGAR FACTORIE",
        "2. Construction of boundary wall of Mahatma Gandhi Inter College in Mohalla Vijay Nagar un",
        "3. Construction work of  residential building of police Chauki Gumawan Thana Shivgarh on t"
      ]
    },
    {
      "name": "Maharashtra",
      "state": "Maharashtra",
      "tenders_seen": 23,
      "status": "ok",
      "sample_titles": [
        "1. Imp and Passage and Drainage System  Near Balkrishna Varekar Room No 847, Adarsh Nagar ",
        "2. E Tender Notice No.01 for 2026-27_01",
        "3. Krushi and Falotpadan Vibhag - Vari - Prasiddhi Upakram"
      ]
    },
    {
      "name": "Rajasthan",
      "state": "Rajasthan",
      "tenders_seen": 23,
      "status": "ok",
      "sample_titles": [
        "1. Construction of Dome in Govt. Senior Secondary School Semaliya, GP Semaliya Block Chitt",
        "2. Construction of 2 Class Rooms in Govt. Senior Secondary School at Segwa, GP Semaliya Bl",
        "3. 03/2026-27 GP DADUBASNI MATERIAL SUPPLY"
      ]
    },
    {
      "name": "Madhya Pradesh",
      "state": "Madhya Pradesh",
      "tenders_seen": 23,
      "status": "ok",
      "sample_titles": [
        "1. Construction work of District Institute of Education and Training COE at Dist. Ujjain M",
        "2. Construction work of District Institute of Education and Training COE at Dist. Narsingh",
        "3. Construction of Sports complex at Dist. Neemuch M.P.. NIT-84"
      ]
    },
    {
      "name": "West Bengal",
      "state": "West Bengal",
      "tenders_seen": 23,
      "status": "ok",
      "sample_titles": [
        "1. Additional works for repairing and laying HDPE pipe line, sluice valve chamber and othe",
        "2. WBPHED/EE/TD/NIeT_01/2026-2027",
        "3. 486-WBSWC-17034/1/2024-FOOD SEC DATED 07-07-20263rd Call"
      ]
    },
    {
      "name": "Tamil Nadu",
      "state": "Tamil Nadu",
      "tenders_seen": 23,
      "status": "ok",
      "sample_titles": [
        "1. Construction of Culvert from Kattukandigai in Asanallikuppam panchayat",
        "2.  Construction of 5 TPD Micro Compost Centre  MCC  in ward No.33",
        "3. Construction of 5 TPD Micro Compost Centre  MCC   in ward No.36"
      ]
    },
    {
      "name": "Punjab",
      "state": "Punjab",
      "tenders_seen": 23,
      "status": "ok",
      "sample_titles": [
        "1. CONST OF 2 NO. LAVATORY BLOCK OF SIZE 28-9x18-3 AT NGM DHURI MC DHURI DISTT. SANGRUR MB",
        "2. PROVIDING AND FIXING 3 NO. CATTLE CATCHERS AT NGM DHURI, MC  DHURI DISTT. SANGRUR  (MB ",
        "3. S/E of Streetlights at Moti Bagh Gurdwara Sahib Patiala. Est cost Rs. 10.56 lacs dt 16/"
      ]
    },
    {
      "name": "Haryana",
      "state": "Haryana",
      "tenders_seen": 23,
      "status": "ok",
      "sample_titles": [
        "1. Repair of HSVP Staff Qtrs. and Repair of Boundary Wall and Chambers at TWell No. G 1  G",
        "2. Stone Retaining Wall at RD 12.320 Km on Augmantation Canal.",
        "3. Repair and maintenance of staff quarter H.No. 07, MCF Officers Colony allotted to Sh. P"
      ]
    },
    {
      "name": "Odisha",
      "state": "Odisha",
      "tenders_seen": 23,
      "status": "ok",
      "sample_titles": [
        "1. Construction of RI Office cum Residence Building at Dihakula under Binjharpur Tahasil i",
        "2. Repair and Maintenance of R.I office cum Residense at Belamguda_building in the distric",
        "3. Repair and Maintenance of Revenue Rest Shed at Chandrapur building in the district of R"
      ]
    },
    {
      "name": "Jharkhand",
      "state": "Jharkhand",
      "tenders_seen": 23,
      "status": "ok",
      "sample_titles": [
        "1. Faecal Sludge and Septage Management under Jamshedpur Notified Area Committee Hurlung J",
        "2. Waste Water management System Drains- Nimbhatta Baridih Basti and Bihari Basti underJam",
        "3. Detailed Estimate for Installation of  Audio System with MIC in all the Court rooms ofC"
      ]
    },
    {
      "name": "Himachal Pradesh",
      "state": "Himachal Pradesh",
      "tenders_seen": 23,
      "status": "ok",
      "sample_titles": [
        "1. Lot No 3/2025-26/Dalhousie (R.A)",
        "2. Lot No 8/2026-27/Dalhousie (R.A)",
        "3. Lot No 10/2026-27/Dalhousie (R.A)"
      ]
    },
    {
      "name": "Uttarakhand",
      "state": "Uttarakhand",
      "tenders_seen": 23,
      "status": "ok",
      "sample_titles": [
        "1. Design, supply, erection, commission of Sugar Bin System along with sugar hopper (multi",
        "2. Supply of Utility Vehicle",
        "3. Supply of Tendem Vibratory Walk Behind Roller"
      ]
    },
    {
      "name": "Chhattisgarh",
      "state": "Chhattisgarh",
      "tenders_seen": 0,
      "status": "HTTPSConnectionPool(host='eproc.cgstate.gov.in', port=443): Max retries exceeded with url: /nicgep/app (Caused by ConnectTimeoutError(<HTTPSConnection(host='eproc.cgstate.gov.in', port=443) at 0x7fd6d439a190>, 'Connection to eproc.cgstate.gov.in timed out. (connect timeout=25)'))",
      "sample_titles": []
    },
    {
      "name": "Assam",
      "state": "Assam",
      "tenders_seen": 23,
      "status": "ok",
      "sample_titles": [
        "1. Selection of Concessionaire for Moving Bed Reactor (MBBR) technology with Lamella Clari",
        "2. Service connection of 256 nos. UE School",
        "3. Consultancy Services for the Development of a Children Park at the Bank of Brahmaputra "
      ]
    },
    {
      "name": "Kerala",
      "state": "Kerala",
      "tenders_seen": 23,
      "status": "ok",
      "sample_titles": [
        "1. Annual Plan-2026-27 OF PANDIKKAD GP-ESTIMATE FOR URGENT MAINTENANCE WORK AT GMLP SCHOOL",
        "2. DEPOSIT-Construction of four new septic tank and maintenance of existing septic tanks f",
        "3. 1754098/26-LAC-ADS-ADAPILLY ROAD TARRING WITH BMBC IN DIV 37-KMC-General Civil Work"
      ]
    },
    {
      "name": "Jammu and Kashmir",
      "state": "Jammu and Kashmir",
      "tenders_seen": 23,
      "status": "ok",
      "sample_titles": [
        "1. Construction of protection wall across the land of fisheries Department adjacent to the",
        "2. Upgradation of work of steel Bridge with iron fencing on both sides near Fisherman colo",
        "3. Procurement of Key Materials for MGNREGA Works For Panchayat Halqa  Dangerpora PATTAN"
      ]
    }
  ],
  "new_matches_found": 0
}