{
  "checked_at_utc": "2026-07-22 08:24:53",
  "portals": [
    {
      "name": "CPPP - Central Government (all ministries)",
      "state": "Central",
      "tenders_seen": 23,
      "status": "ok",
      "sample_titles": [
        "1. Comprehensive Annual Maintenance Contract of 40 MT type Fully Electronic (Computerized)",
        "2.  Running and maintenance of DDA Roshanara club for the year 2026-27.",
        "3. Superior Kerosene Oil as per IS 1459-Latest version and supplied in suitable tankers."
      ]
    },
    {
      "name": "Uttar Pradesh",
      "state": "Uttar Pradesh",
      "tenders_seen": 23,
      "status": "ok",
      "sample_titles": [
        "1. WARD NO 21 TARNA CHATRIPUR ME DADA CHAKKI KE GHAR SE RAMJANMA PRASHAD KE GHAR RAK ROAD ",
        "2. WARD NO 37 DANIYALPUR ANTARGAT PANCHKOSHI CHAURAHA SE CHAURA MATA MANDIR VIMLA DEVI KE ",
        "3. WARD NO 20 LODHAN ANTARGAT SAI UPVAN SE MANISH SINGH KE GHAR SE HOTE HUEE VIJAY KAPOOR "
      ]
    },
    {
      "name": "Maharashtra",
      "state": "Maharashtra",
      "tenders_seen": 23,
      "status": "ok",
      "sample_titles": [
        "1. Estimate No. 132406 of 2026-27",
        "2. RATE CONCTRACT OF BUILDING MATERIAL FOR FINANCIAL YEAR 2026-27 AT. GRAMPANCHAYAT CHICHO",
        "3. Design and build of refurbishing AGRC conference hall, chambers, open offices of SRA, B"
      ]
    },
    {
      "name": "Rajasthan",
      "state": "Rajasthan",
      "tenders_seen": 23,
      "status": "ok",
      "sample_titles": [
        "1. SITC Leminar Flow Unit at District Hospital Hindaun distt karauli",
        "2. Garbage collection and complete cleaning of roads, drains, sewers, etc. from wards numb",
        "3. Range Bhilwara - Forest Development Works"
      ]
    },
    {
      "name": "Madhya Pradesh",
      "state": "Madhya Pradesh",
      "tenders_seen": 23,
      "status": "ok",
      "sample_titles": [
        "1. Tender for sale of LIG houses at Kokta Project",
        "2. Patient food supply",
        "3. Work for comprehensive annual maintenance contract for HITACHI Hi-Rel make 2x2KVA UPS s"
      ]
    },
    {
      "name": "West Bengal",
      "state": "West Bengal",
      "tenders_seen": 23,
      "status": "ok",
      "sample_titles": [
        "1. BGP/76/APAS/26",
        "2. BGP/76/APAS/26",
        "3. WBPHED/24_33/EE/BOLMD/2026-27"
      ]
    },
    {
      "name": "Tamil Nadu",
      "state": "Tamil Nadu",
      "tenders_seen": 23,
      "status": "ok",
      "sample_titles": [
        "1. Providing Extention of Pipeline at Village in Thottikuppam Panchayat",
        "2. Bus Stand Shop No 13 Auction",
        "3. 3167/A3/2026/GPTC/AUNDIPATTI"
      ]
    },
    {
      "name": "Punjab",
      "state": "Punjab",
      "tenders_seen": 23,
      "status": "ok",
      "sample_titles": [
        "1. Construction of boundary wall at back side of Gynae ward, DH Sangrur (3rd Call)",
        "2. Supply of Rice Bran, Rice Bran Extraction and Maize at Kapurthala and Gidderbaha Plant",
        "3. SALE OF SUGAR"
      ]
    },
    {
      "name": "Haryana",
      "state": "Haryana",
      "tenders_seen": 23,
      "status": "ok",
      "sample_titles": [
        "1. Tender for purchasing books for e-library, Sector-12, Faridabad",
        "2. Supply, Installation and Commissioning of 30 KWP On Grid Inverter for Roof Top Solar",
        "3. Forestry Work maintenence"
      ]
    },
    {
      "name": "Odisha",
      "state": "Odisha",
      "tenders_seen": 23,
      "status": "ok",
      "sample_titles": [
        "1. Construction of road from Biswanathpur IB road to Jaripada Panchayat office  under MMSY",
        "2. Construction of Krushak Bazar and Hata at Mining Road in Kendujhargada Municipality",
        "3. Construction of road from Khetrapal canal Bridge to Charigharia via Kayapalli under MMS"
      ]
    },
    {
      "name": "Jharkhand",
      "state": "Jharkhand",
      "tenders_seen": 23,
      "status": "ok",
      "sample_titles": [
        "1. Request for Proposal for Selection of Cloud Service Provider for providing Cloud Infras",
        "2. 1. Construction of 4  ACR  in Govt Secondary School Jitiyatoli   2. Construction of 04 ",
        "3. 1. Construction of 4 ACR in Mahamana Malviya H.S Konmerla  2. Construction of 04 ACR in"
      ]
    },
    {
      "name": "Himachal Pradesh",
      "state": "Himachal Pradesh",
      "tenders_seen": 23,
      "status": "ok",
      "sample_titles": [
        "1. NO.HPSEBL/OCM/NIT-11/2026-27",
        "2. NO.HPSEBL/OCM/NIT-10/2026-27",
        "3. Fabrication, Supply, erection, Testing and commissioning of Galvanized iron perforated "
      ]
    },
    {
      "name": "Uttarakhand",
      "state": "Uttarakhand",
      "tenders_seen": 23,
      "status": "ok",
      "sample_titles": [
        "1. Hiring of vehicle for AE civil  haldwani",
        "2. ESWC(H)/07/2026-2027",
        "3. Construction of the Road from the Main Road to Meghwal Basti in Peliyo village, Dehradu"
      ]
    },
    {
      "name": "Chhattisgarh",
      "state": "Chhattisgarh",
      "tenders_seen": 0,
      "status": "HTTPSConnectionPool(host='eproc.cgstate.gov.in', port=443): Max retries exceeded with url: /nicgep/app (Caused by ConnectTimeoutError(<HTTPSConnection(host='eproc.cgstate.gov.in', port=443) at 0x7f184a920f90>, 'Connection to eproc.cgstate.gov.in timed out. (connect timeout=25)'))",
      "sample_titles": []
    },
    {
      "name": "Assam",
      "state": "Assam",
      "tenders_seen": 23,
      "status": "ok",
      "sample_titles": [
        "1. Construction of Market Building G1 Ground Floor at Sorbhog Bazar near Primary Health ce",
        "2. Repairing of boundary drainage system including apron and sanitary fitting with water s",
        "3. Setting up of 13 No of open ring well"
      ]
    },
    {
      "name": "Kerala",
      "state": "Kerala",
      "tenders_seen": 23,
      "status": "ok",
      "sample_titles": [
        "1. Marking for Third Silvicultural Thinning in 2005 Cheppilakkode Teak Plantation 33 Ha in",
        "2. 03/AEE/2026-27-Re tender",
        "3. Maintanance of Rest Room and leak rectification in Vanasree Hall in Thenmala Forest Div"
      ]
    },
    {
      "name": "Jammu and Kashmir",
      "state": "Jammu and Kashmir",
      "tenders_seen": 23,
      "status": "ok",
      "sample_titles": [
        "1. Improvement of water supply to Check Rawalpora by way of providing 80/50/25mm dia GI pi",
        "2. CONSTRUCTION OF A 66 KV SINGLE CIRCUIT LINE FOR REROUTING OF THE FLOOD-AFFECTED CHANN C",
        "3. Cleaning of roads, drains, Cutting of Bushes lifting of Garbage/Mulba using Labour and "
      ]
    }
  ],
  "new_matches_found": 0
}