{
  "checked_at_utc": "2026-07-15 07:31:36",
  "portals": [
    {
      "name": "CPPP - Central Government (all ministries)",
      "state": "Central",
      "tenders_seen": 23,
      "status": "ok",
      "sample_titles": [
        "1. Lifting of garbage in and around nearby village of  JN Port  area for the year 2026-27",
        "2. Repair and maintenance of double storey pre-fabricated barrack (being used as Sos barra",
        "3. Installation of Bird Spikes and net in DJAC Building, Zone-4 Academic Area."
      ]
    },
    {
      "name": "Uttar Pradesh",
      "state": "Uttar Pradesh",
      "tenders_seen": 23,
      "status": "ok",
      "sample_titles": [
        "1. CIVIL RECTIFICATION AND STRENGTHENING WORK OF CONTROL ROOM BUILDING, E.E. EDD OFFICE, S",
        "2. Work of installation of Partition Wall AC Air Cooler and Water Cooler in the District H",
        "3. Strengthening of Road (P/L DBM andd BC work Block A B and C in Sector-19) Noida"
      ]
    },
    {
      "name": "Maharashtra",
      "state": "Maharashtra",
      "tenders_seen": 23,
      "status": "ok",
      "sample_titles": [
        "1. eTENDER FOR 2026-27",
        "2. E-TENDER NOTICE NO 02 FOR 22026-2027",
        "3. PROPOSED SUPPLYING AND INSTALLATION OFSANT BHAGWAN BABA STATUE IN PARLI CITY for mc par"
      ]
    },
    {
      "name": "Rajasthan",
      "state": "Rajasthan",
      "tenders_seen": 23,
      "status": "ok",
      "sample_titles": [
        "1. CHANDNA SADAK MARG PAR SARVJANIK BHUMI ME TIN SHED MAYE INTERLOCKING KHARANJA EVAM ANYA",
        "2. Construction of Sewer line and manholes from Sk deora school to bhinda park and Bhoothn",
        "3. SITC of Fire Alarm System at District Drug Warehouse Sethi Colony Jaipur"
      ]
    },
    {
      "name": "Madhya Pradesh",
      "state": "Madhya Pradesh",
      "tenders_seen": 23,
      "status": "ok",
      "sample_titles": [
        "1. CONSTRUCTION OF AKHADA AT WARD NO 06 HATOD",
        "2. Construction work of Entrance Gate in Scheme No. 41 and 64 JDA Jabalpur",
        "3. Tender for Semi Turn key Basis FOR Feeder Separation Bifurcation 11 KV Gumadiya Mix Niw"
      ]
    },
    {
      "name": "West Bengal",
      "state": "West Bengal",
      "tenders_seen": 23,
      "status": "ok",
      "sample_titles": [
        "1. Construction of SiyaldangaZahirthan AWC AWC No. 95 at Radhaballavpur Samdi under Salanp",
        "2. NIe-T-02/Sl-08/2026-27",
        "3. NIe-T-02/Sl-09/2026-27"
      ]
    },
    {
      "name": "Tamil Nadu",
      "state": "Tamil Nadu",
      "tenders_seen": 23,
      "status": "ok",
      "sample_titles": [
        "1. PURCHASE OF WORK TABLE",
        "2. Providing Painting Work with PVC Tank and Incinerator at Karumandapam North Street Toil",
        "3. Maintenance and Repairs to handpumps in Zonv V Div IV."
      ]
    },
    {
      "name": "Punjab",
      "state": "Punjab",
      "tenders_seen": 23,
      "status": "ok",
      "sample_titles": [
        "1. Desilting of Main and Branch Sewer Line at Various Places in Neelpur area Bhoglan road ",
        "2. Engagement of Special Third Party Independent Techno Financial Auditor for Techno Finan",
        "3. Engagement of Special Third Party Independent Techno Financial Auditor for Techno Finan"
      ]
    },
    {
      "name": "Haryana",
      "state": "Haryana",
      "tenders_seen": 23,
      "status": "ok",
      "sample_titles": [
        "1. State Scheme Forestry Mts. Works Kathura Block",
        "2. State Scheme Forestry Mts. Works Moi Block",
        "3. ROSpares"
      ]
    },
    {
      "name": "Odisha",
      "state": "Odisha",
      "tenders_seen": 23,
      "status": "ok",
      "sample_titles": [
        "1. Construction of PWD road to Balara  Kantapada in the District of Puri under MMSY-Transf",
        "2. Construction of Renghalo Bhoisahi to Chhatahara U.P School Road in the district of Puri",
        "3. Construction of Binayakpur  to Khandasahi in the District of Puri under MMSY-Transferre"
      ]
    },
    {
      "name": "Jharkhand",
      "state": "Jharkhand",
      "tenders_seen": 23,
      "status": "ok",
      "sample_titles": [
        "1. Construction of 200 feet Drain  From Rajesh press House to Nala under Govindpur East Pa",
        "2. IRQP Work in Bank More to Joraphatak Road (Total Length -1.90 Km) Under Plan Head For T",
        "3. Special Repair work of Circuit House Lohardaga to BS College Road at 2.0 km. via Budhu "
      ]
    },
    {
      "name": "Himachal Pradesh",
      "state": "Himachal Pradesh",
      "tenders_seen": 23,
      "status": "ok",
      "sample_titles": [
        "1. Restoration of rain damages on Balh to Ropa road Km 0/0 to 5/100. (PDNA-2023)",
        "2. Restoration of rain damages on Thaltukhod to Marh road Km 0/0 to 5/00. (PDNA-2023)",
        "3. Restoration of rain damages on Sahal Garlog road Km 0/0 to 7/530. (PDNA-2023)"
      ]
    },
    {
      "name": "Uttarakhand",
      "state": "Uttarakhand",
      "tenders_seen": 23,
      "status": "ok",
      "sample_titles": [
        "1. REPLACEMENT OF G.I PIPE LINE IN PLACE OF OLD AND DAMAGE PIPE LINE AT YAMUNA COLONY WARD",
        "2. Reconstruction and improvement work on the Kharkyu Motor Road an extension of the Garhs",
        "3. For Shifting of 33 KV line etc."
      ]
    },
    {
      "name": "Chhattisgarh",
      "state": "Chhattisgarh",
      "tenders_seen": 0,
      "status": "HTTPSConnectionPool(host='eproc.cgstate.gov.in', port=443): Max retries exceeded with url: /nicgep/app (Caused by ConnectTimeoutError(<HTTPSConnection(host='eproc.cgstate.gov.in', port=443) at 0x7f563f8b1750>, 'Connection to eproc.cgstate.gov.in timed out. (connect timeout=25)'))",
      "sample_titles": []
    },
    {
      "name": "Assam",
      "state": "Assam",
      "tenders_seen": 23,
      "status": "ok",
      "sample_titles": [
        "1. Selection of Agencies for Digital Promotion including Social Media",
        "2. ENGAGEMENT OF INSURANCE BROKER FOR GROUP MEDICLAIM POLICY OF ASSAM ELECTRICITY GRID COR",
        "3. Overhauling of Station Transformer and Generator Transformer of LTPS APGCL"
      ]
    },
    {
      "name": "Kerala",
      "state": "Kerala",
      "tenders_seen": 23,
      "status": "ok",
      "sample_titles": [
        "1. MLA-SDF-MLA-SDF-2026-27 Pappukutty Memorial Library at Kedamangalam North Paravur Const",
        "2. LAC-ADS-MLA ADS - Anganwadi No. 9, Chazhoor (Nattika Constituency)-Construction of new ",
        "3. LAC-ADS-2022-23 Thodupuzha Municipality Construction of KunnumpuramPeechanikkunnu link "
      ]
    },
    {
      "name": "Jammu and Kashmir",
      "state": "Jammu and Kashmir",
      "tenders_seen": 23,
      "status": "ok",
      "sample_titles": [
        "1. (1) CONSTRUCTION OF COMPUTER ROOM AT GOVT HR. SEC. SCHOOL (GIRLS)REASI.                ",
        "2. Dismantling and reconstruction of food store building at Hiranagar.",
        "3. Construction of Elementary  ACR at Govt MS Salal Kotali Zone Chinkah under PAB SAMAGRA"
      ]
    }
  ],
  "new_matches_found": 0
}